hoba/__init__.py
hoba/cli.py
hoba/gen.py
hoba/sync.py
hoba-0.1.2.dist-info/entry_points.txt
hoba-0.1.2.dist-info/LICENSE
hoba-0.1.2.dist-info/WHEEL
hoba-0.1.2.dist-info/METADATA
hoba-0.1.2.dist-info/RECORD
